{
  "Assets": [
    {
      "Symbol": "NZD",
      "SecType": "CASH",
      "Exchange": "IDEALPRO",
      "Currency": "USD",

      "LowStoploss": 0.6591,
      "HighStoploss": 0.6793,
      "LowTakeprofit": 0.6626,
      "HighTakeprofit": 0.6766,
      "Close": 0.6704,
      "MaxPositionSize": 30000
    },
    {
      "Symbol": "USD",
      "SecType": "CASH",
      "Exchange": "IDEALPRO",
      "Currency": "CAD",

      "LowStoploss": 1.3207,
      "HighStoploss": 1.3450,
      "LowTakeprofit": 1.3260,
      "HighTakeprofit": 1.3397,
      "Close": 1.3328,
      "MaxPositionSize": 30000
    },
    {
      "Symbol": "EUR",
      "SecType": "CASH",
      "Exchange": "IDEALPRO",
      "Currency": "USD",

      "LowStoploss": 1.1332,
      "HighStoploss": 1.1544,
      "LowTakeprofit": 1.1360,
      "HighTakeprofit": 1.1493,
      "Close": 1.1435,
      "MaxPositionSize": 30000
    },
    {
      "Symbol": "AUD",
      "SecType": "CASH",
      "Exchange": "IDEALPRO",
      "Currency": "USD",

      "LowStoploss": 0.7045,
      "HighStoploss": 0.7198,
      "LowTakeprofit": 0.7073,
      "HighTakeprofit": 0.7168,
      "Close": 0.7120,
      "MaxPositionSize": 30000
    }
  ]
}